{
  "data": [
    {
      "id": "some-unique-id-01",
      "data": {
        "type": "song-track",
        "title": "Catch Me I'm Falling",
        "artist": "Pretty Poison",
        "album": "Catch Me I'm Falling"
      }
    },
    {
      "id": "some-unique-id-02",
      "data": {
        "type": "song-track",
        "title": "Nightime",
        "artist": "Pretty Poison",
        "album": "Catch Me I'm Falling"
      }
    },
    {
      "id": "some-unique-id-03",
      "data": {
        "type": "song-track",
        "title": "Closer",
        "artist": "Pretty Poison",
        "album": "Catch Me I'm Falling"
      }
    },
    {
      "id": "beatles-one",
      "data": {
        "type": "song-track",
        "title": "Golden Slumbers",
        "artist": "The Beatles",
        "album": "Abbey Road"
      }
    },
    {
      "id": "addr-id-01",
      "data": {
        "type": "person-contact",
        "first": "Josh",
        "last": "Marinacci",
        "email": "josh@josh.earth"
      }
    },
    {
      "id": "addr-id-02",
      "data": {
        "type": "person-contact",
        "first": "Jesse",
        "last": "Marinacci",
        "email": "dont@email.me"
      }
    },
    {
      "id": "addr-id-03",
      "data": {
        "type": "person-contact",
        "first": "Billy",
        "last": "Bob",
        "email": "billybob@billybob.com"
      }
    },
    {
      "id": "addr-id-04",
      "data": {
        "type": "person-contact",
        "first": "Tony",
        "last": "Stark",
        "email": "tony@stark.com"
      }
    }
  ]
}
